myanimelist_downloader/__init__.py
myanimelist_downloader/command_line.py
myanimelist_downloader/downloader.py
myanimelist_downloader/driver.py
myanimelist_downloader/list.py
myanimelist_downloader-0.0.9.dist-info/LICENSE
myanimelist_downloader-0.0.9.dist-info/METADATA
myanimelist_downloader-0.0.9.dist-info/WHEEL
myanimelist_downloader-0.0.9.dist-info/entry_points.txt
myanimelist_downloader-0.0.9.dist-info/top_level.txt
myanimelist_downloader-0.0.9.dist-info/RECORD
