Metadata-Version: 2.1
Name: myanimelist-downloader
Version: 0.0.9
Summary: Download manga and anime lists from MyAnimeList.
Home-page: https://github.com/SanteriHetekivi/myanimelist_downloader
Author: Santeri Hetekivi
Author-email: development@hetekivi.com
Project-URL: Bug Tracker, https://github.com/SanteriHetekivi/myanimelist_downloader/issues
Classifier: Programming Language :: Python :: 3
Classifier: License :: OSI Approved :: Apache Software License
Classifier: Operating System :: OS Independent
Requires-Python: >=3.10
License-File: LICENSE
Requires-Dist: password-credentials (==0.0.6)
Requires-Dist: dir-handeler (==0.0.1)
Requires-Dist: selenium (==4.1.3)
Requires-Dist: webdriver-manager (==3.5.4)
Requires-Dist: python-dotenv (==0.20.0)
